{"cameraMode":{"drawMode":0,"name":"Shaded","section":"Shading Mode"},"sceneLighting":false,"audioPlay":false,"sceneViewState":{"m_AlwaysRefresh":false,"showFog":true,"showSkybox":false,"showFlares":true,"showImageEffects":true,"showParticleSystems":true,"showVisualEffectGraphs":true,"m_FxEnabled":true},"in2DMode":false,"pivot":{"x":7.0,"y":0.5,"z":51.2400016784668},"rotation":{"x":-0.22878924012184144,"y":-0.03707275167107582,"z":0.008718650788068772,"w":-0.9727482795715332},"size":2.9790101051330568,"orthographic":true}